<odoo>
    <data>

        <!-- Organization Views -->

        <record id="hc_res_organization_view_search" model="ir.ui.view">
            <field name="name">Organization Search</field>
            <field name="model">hc.res.organization</field>
            <field name="arch" type="xml">
                <search string="Organizations">
                    <field name="partner_id"/>
                    <field name="is_active"/>
                    <field name="type_ids"/>
                    <field name="part_of_id"/>
                    <field name="company_id"/>
                </search>
            </field>
        </record>

        <record id="hc_res_organization_view_tree" model="ir.ui.view">
            <field name="name">Organization Tree</field>
            <field name="model">hc.res.organization</field>
            <field name="arch" type="xml">
                <tree string="Organizations">
                    <field name="partner_id"/>
                    <field name="is_active"/>
                    <field name="type_ids" widget="many2many_tags"/>
                    <field name="part_of_id"/>
                    <field name="company_id"/>
                </tree>
            </field>
        </record>

        <record id="hc_res_organization_view_form" model="ir.ui.view">
            <field name="name">Organization Form</field>
            <field name="model">hc.res.organization</field>
            <field name="arch" type="xml">
                <form string="Organization">
                    <sheet>
                        <h1>
                            <field name="name" default_focus="1" placeholder="Name"/>
                        </h1>
                        <group>
                            <group>
                                <field name="partner_id"/>
                                <field name="is_active"/>
                                <field name="type_ids" widget="many2many_tags"/>
                            </group>
                            <group>
                                <field name="part_of_id" placeholder="Organization"/>
                                <field name="company_id" string="Odoo Company"/>
                            </group>
                        </group>
                        <notebook>
                            <page string="Contacts">
                                <field name="contact_ids" mode="tree">
                                    <tree>
                                        <field name="person_id"/>
                                        <field name="purpose_id"/>
                                    </tree>
                                    <form>
                                        <sheet>
                                            <h1>
                                                <field name="person_id" placeholder="Name"/>
                                            </h1>
                                            <group>
                                                <group>
                                                    <field name="purpose_id"/>
                                                </group>
                                                <group>
                                                    <field name="address_id"/>
                                                </group>
                                            </group>
                                            <notebook>
                                                <page string="Telecom">
                                                    <field name="telecom_ids" mode="tree">
                                                        <tree default_order="is_preferred,rank">
                                                            <field name="is_preferred"/>
                                                            <field name="rank"/>
                                                            <field name="use"/>
                                                            <field name="telecom_id"/>
                                                            <field name="start_date"/>
                                                            <field name="end_date"/>
                                                        </tree>
                                                        <form>
                                                            <sheet>
                                                                <h1>
                                                                    <field name="telecom_id"/>
                                                                </h1>
                                                                <field name="use" widget="radio" options="{'horizontal': true}"/>
                                                                <group>
                                                                    <group>
                                                                        <field name="rank"/>
                                                                        <field name="is_preferred"/>
                                                                        <field name="is_active"/>
                                                                        <field name="start_date" placeholder="Valid From"/>
                                                                        <field name="end_date" placeholder="Valid To"/>
                                                                    </group>
                                                                </group>
                                                            </sheet>
                                                        </form>
                                                    </field>
                                                </page>
                                            </notebook>
                                        </sheet>
                                    </form>
                                </field>
                            </page>
                            <page string="Identifiers">
                                <field name="identifier_ids" mode="tree">
                                    <tree default_order="is_preferred">
                                        <field name="is_preferred"/>
                                        <field name="name"/>
                                        <field name="value"/>
                                        <field name="start_date"/>
                                        <field name="end_date"/>
                                    </tree>
                                    <form>
                                        <sheet>
                                            <h1>
                                                <field name="name" placeholder="Identifier"/>
                                            </h1>
                                            <group col="4" colspan="4">
                                                <group>
                                                    <field name="value"/>
                                                    <field name="system"/>
                                                    <field name="is_preferred"/>
                                                    <field name="is_active"/>
                                                </group>
                                                <group>
                                                    <field name="start_date" placeholder="Valid From"/>
                                                    <field name="end_date" placeholder="Valid To"/>
                                               </group>
                                            </group>
                                        </sheet>
                                    </form>
                                </field>
                            </page>
                            <page string="Aliases">
                                <field name="alias_ids" mode="tree">
                                    <tree>
                                        <field name="alias" editable="bottom"/>
                                    </tree>
                                    <form>
                                        <sheet>
                                            <group>
                                                <group>
                                                </group>
                                                <group>
                                                </group>
                                            </group>
                                        </sheet>
                                    </form>
                                </field>
                            </page>
                            <page string="Telecom">
                                <field name="telecom_ids" mode="tree">
                                    <tree default_order="is_preferred,rank">
                                        <field name="is_preferred"/>
                                        <field name="rank"/>
                                        <field name="use"/>
                                        <field name="telecom_id"/>
                                        <field name="start_date"/>
                                        <field name="end_date"/>
                                    </tree>
                                    <form>
                                        <sheet>
                                            <h1>
                                                <field name="telecom_id"/>
                                            </h1>
                                            <field name="use" widget="radio" options="{'horizontal': true}"/>
                                            <group>
                                                <group>
                                                    <field name="rank"/>
                                                    <field name="is_preferred"/>
                                                    <field name="is_active"/>
                                                    <field name="start_date" placeholder="Valid From"/>
                                                    <field name="end_date" placeholder="Valid To"/>
                                                </group>
                                            </group>
                                        </sheet>
                                    </form>
                                </field>
                            </page>
                            <page string="Addresses">
                                <field name="address_ids" mode="tree">
                                    <tree default_order="is_preferred">
                                        <field name="is_preferred"/>
                                        <field name="use"/>
                                        <field name="line1"/>
                                        <field name="line2"/>
                                        <field name="city_id"/>
                                        <field name="postal_code_id"/>
                                        <field name="country_id"/>
                                        <field name="start_date"/>
                                        <field name="end_date"/>
                                    </tree>
                                    <form>
                                        <sheet>
                                            <h1>
                                                <field name="address_id" class="oe_no_button"/>
                                            </h1>
                                            <field name="use" widget="radio" options="{'horizontal': true}"/>
                                            <group>
                                                <group>
                                                    <field name="is_preferred"/>
                                                    <field name="is_active"/>
                                                    <field name="start_date" placeholder="Valid From"/>
                                                    <field name="end_date" placeholder="Valid To"/>
                                                </group>
                                            </group>
                                        </sheet>
                                    </form>
                                </field>
                            </page>
                            <page string="Endpoints">
                                <field name="endpoint_ids" mode="tree">
                                    <tree>
<!--                                         <field name="endpoint_id"/> -->
                                    </tree>
                                    <form>
                                        <sheet>
                                            <group>
                                                <group>
<!--                                                     <field name="endpoint_id"/> -->
                                                </group>
                                                <group>
                                                </group>
                                            </group>
                                        </sheet>
                                    </form>
                                </field>
                            </page>
                            <page string="Locations">
                                <field name="location_ids" mode="tree">
                                    <tree>
                                    </tree>
                                    <form>
                                        <sheet>
                                            <group>
                                                <group>
                                                </group>
                                                <group>
                                                </group>
                                            </group>
                                        </sheet>
                                    </form>
                                </field>
                            </page>
                            <page string="Meta">
                                <form>
                                    <sheet>
                                        <group string="Resource">
                                            <group>
                                                <field name="identifier"/>
                                                <field name="implicit_rules"/>
                                                <field name="language_id"/>
                                                <field name="meta_id"/>
                                            </group>
                                            <group>
                                            </group>
                                        </group>
                                        <group string="Domain Resource">
                                            <group>
                                                <field name="text_id"/>
                                            </group>
                                            <group>
                                            </group>
                                        </group>
                                        <notebook>
                                            <page string="Contained">
                                                <field name="contained_ids" mode="tree">
                                                    <tree>
                                                        <field name="identifier"/>
                                                        <field name="meta_id"/>
                                                        <field name="implicit_rules"/>
                                                        <field name="language_id"/>
                                                    </tree>
                                                    <form>
                                                        <sheet>
                                                            <group>
                                                                <group>
                                                                    <field name="identifier"/>
                                                                    <field name="meta_id"/>
                                                                    <field name="implicit_rules"/>
                                                                    <field name="language_id"/>
                                                                </group>
                                                                <group>
                                                                </group>
                                                            </group>
                                                        </sheet>
                                                    </form>
                                                </field>
                                            </page>
                                            <page string="Extensions">
                                                <field name="extension_ids" mode="tree">
                                                    <tree>
                                                        <field name="url"/>
                                                        <field name="value_name"/>
                                                        <field name="value_type"/>
                                                    </tree>
                                                    <form>
                                                        <sheet>
                                                            <group>
                                                                <group>
                                                                    <field name="url"/>
                                                                    <field name="value_name"/>
                                                                    <field name="value_type" class="oe_edit_only"/>
                                                                    <field name="value_integer" class="oe_edit_only" attrs="{'invisible': [('value_type','!=','integer')], 'required': [('value_type','=','integer')]}"/>
                                                                    <field name="value_decimal" class="oe_edit_only" attrs="{'invisible': [('value_type','!=','decimal')], 'required': [('value_type','=','decimal')]}"/>
                                                                    <field name="value_date_time" class="oe_edit_only" attrs="{'invisible': [('value_type','!=','date_time')], 'required': [('value_type','=','date_time')]}"/>
                                                                    <field name="value_date" class="oe_edit_only" attrs="{'invisible': [('value_type','!=','date')], 'required': [('value_type','=','date')]}"/>
                                                                    <field name="value_instant" class="oe_edit_only" attrs="{'invisible': [('value_type','!=','instant')], 'required': [('value_type','=','instant')]}"/>
                                                                    <field name="value_string" class="oe_edit_only" attrs="{'invisible': [('value_type','!=','string')], 'required': [('value_type','=','string')]}"/>
                                                                    <field name="value_uri" class="oe_edit_only" attrs="{'invisible': [('value_type','!=','uri')], 'required': [('value_type','=','uri')]}"/>
                                                                    <field name="value_boolean" class="oe_edit_only" attrs="{'invisible': [('value_type','!=','boolean')], 'required': [('value_type','=','boolean')]}"/>
                                                                    <field name="value_code_id" class="oe_edit_only" attrs="{'invisible': [('value_type','!=','code')], 'required': [('value_type','=','code')]}"/>
                                                                    <field name="value_markdown" class="oe_edit_only" attrs="{'invisible': [('value_type','!=','markdown')], 'required': [('value_type','=','markdown')]}"/>
                                                                    <field name="value_base_64_binary" class="oe_edit_only" attrs="{'invisible': [('value_type','!=','base_64_binary')], 'required': [('value_type','=','base_64_binary')]}"/>
                                                                    <field name="value_coding_id" class="oe_edit_only" attrs="{'invisible': [('value_type','!=','coding')], 'required': [('value_type','=','coding')]}"/>
                                                                    <field name="value_codeable_concept_id" class="oe_edit_only" attrs="{'invisible': [('value_type','!=','codeable_concept')], 'required': [('value_type','=','codeable_concept')]}"/>
                                                                    <field name="value_attachment_id" class="oe_edit_only" attrs="{'invisible': [('value_type','!=','attachment')], 'required': [('value_type','=','attachment')]}"/>
                                                                    <field name="value_identifier_id" class="oe_edit_only" attrs="{'invisible': [('value_type','!=','identifier')], 'required': [('value_type','=','identifier')]}"/>
                                                                    <field name="value_quantity" class="oe_edit_only" attrs="{'invisible': [('value_type','!=','quantity')], 'required': [('value_type','=','quantity')]}"/>
                                                                    <field name="value_quantity_uom_id" class="oe_edit_only" attrs="{'invisible': [('value_type','!=','quantity')], 'required': [('value_type','=','quantity')]}"/>
                                                                    <field name="value_range" class="oe_edit_only" attrs="{'invisible': [('value_type','!=','range')], 'required': [('value_type','=','range')]}"/>
                                                                    <field name="value_period" class="oe_edit_only" attrs="{'invisible': [('value_type','!=','period')], 'required': [('value_type','=','period')]}"/>
                                                                    <field name="value_period_uom_id" class="oe_edit_only" attrs="{'invisible': [('value_type','!=','period')], 'required': [('value_type','=','period')]}"/>
                                                                    <field name="value_ratio" class="oe_edit_only" attrs="{'invisible': [('value_type','!=','ratio')], 'required': [('value_type','=','ratio')]}"/>
                                                                    <field name="value_human_name_id" class="oe_edit_only" attrs="{'invisible': [('value_type','!=','human_name')], 'required': [('value_type','=','human_name')]}"/>
                                                                    <field name="value_address_id" class="oe_edit_only" attrs="{'invisible': [('value_type','!=','address')], 'required': [('value_type','=','address')]}"/>
                                                                    <field name="value_contact_point_id" class="oe_edit_only" attrs="{'invisible': [('value_type','!=','contact_point')], 'required': [('value_type','=','contact_point')]}"/>
                                                                    <field name="value_timing_id" class="oe_edit_only" attrs="{'invisible': [('value_type','!=','timing')], 'required': [('value_type','=','timing')]}"/>
                                                                    <field name="value_signature_id" class="oe_edit_only" attrs="{'invisible': [('value_type','!=','signature')], 'required': [('value_type','=','signature')]}"/>
                                                                    <field name="value_reference_id" class="oe_edit_only" attrs="{'invisible': [('value_type','!=','reference')], 'required': [('value_type','=','reference')]}"/>
                                                                    <field name="value_time" class="oe_edit_only" attrs="{'invisible': [('value_type','!=','time')], 'required': [('value_type','=','time')]}"/>
                                                                    <field name="value_oid" class="oe_edit_only" attrs="{'invisible': [('value_type','!=','oid')], 'required': [('value_type','=','oid')]}"/>
                                                                    <field name="value_id" class="oe_edit_only" attrs="{'invisible': [('value_type','!=','id')], 'required': [('value_type','=','id')]}"/>
                                                                    <field name="value_unsigned_int" class="oe_edit_only" attrs="{'invisible': [('value_type','!=','unsigned_int')], 'required': [('value_type','=','unsigned_int')]}"/>
                                                                    <field name="value_positive_int" class="oe_edit_only" attrs="{'invisible': [('value_type','!=','positive_int')], 'required': [('value_type','=','positive_int')]}"/>
                                                                    <field name="value_annotation_id" class="oe_edit_only" attrs="{'invisible': [('value_type','!=','annotation')], 'required': [('value_type','=','annotation')]}"/>
                                                                    <field name="value_sampled_data_id" class="oe_edit_only" attrs="{'invisible': [('value_type','!=','sampled_data')], 'required': [('value_type','=','sampled_data')]}"/>
                                                                    <field name="value_meta_id" class="oe_edit_only" attrs="{'invisible': [('value_type','!=','meta')], 'required': [('value_type','=','meta')]}"/>
                                                                </group>
                                                                <group>
                                                                </group>
                                                            </group>
                                                        </sheet>
                                                    </form>
                                                </field>
                                            </page>
                                            <page string="Modifier Extensions">
                                                <field name="modifier_extension_ids" mode="tree">
                                                    <tree>
                                                        <field name="url"/>
                                                        <field name="value_name"/>
                                                        <field name="value_type"/>
                                                    </tree>
                                                    <form>
                                                        <sheet>
                                                            <group>
                                                                <group>
                                                                    <field name="url"/>
                                                                    <field name="value_name"/>
                                                                    <field name="value_type" class="oe_edit_only"/>
                                                                    <field name="value_integer" class="oe_edit_only" attrs="{'invisible': [('value_type','!=','integer')], 'required': [('value_type','=','integer')]}"/>
                                                                    <field name="value_decimal" class="oe_edit_only" attrs="{'invisible': [('value_type','!=','decimal')], 'required': [('value_type','=','decimal')]}"/>
                                                                    <field name="value_date_time" class="oe_edit_only" attrs="{'invisible': [('value_type','!=','date_time')], 'required': [('value_type','=','date_time')]}"/>
                                                                    <field name="value_date" class="oe_edit_only" attrs="{'invisible': [('value_type','!=','date')], 'required': [('value_type','=','date')]}"/>
                                                                    <field name="value_instant" class="oe_edit_only" attrs="{'invisible': [('value_type','!=','instant')], 'required': [('value_type','=','instant')]}"/>
                                                                    <field name="value_string" class="oe_edit_only" attrs="{'invisible': [('value_type','!=','string')], 'required': [('value_type','=','string')]}"/>
                                                                    <field name="value_uri" class="oe_edit_only" attrs="{'invisible': [('value_type','!=','uri')], 'required': [('value_type','=','uri')]}"/>
                                                                    <field name="value_boolean" class="oe_edit_only" attrs="{'invisible': [('value_type','!=','boolean')], 'required': [('value_type','=','boolean')]}"/>
                                                                    <field name="value_code_id" class="oe_edit_only" attrs="{'invisible': [('value_type','!=','code')], 'required': [('value_type','=','code')]}"/>
                                                                    <field name="value_markdown" class="oe_edit_only" attrs="{'invisible': [('value_type','!=','markdown')], 'required': [('value_type','=','markdown')]}"/>
                                                                    <field name="value_base_64_binary" class="oe_edit_only" attrs="{'invisible': [('value_type','!=','base_64_binary')], 'required': [('value_type','=','base_64_binary')]}"/>
                                                                    <field name="value_coding_id" class="oe_edit_only" attrs="{'invisible': [('value_type','!=','coding')], 'required': [('value_type','=','coding')]}"/>
                                                                    <field name="value_codeable_concept_id" class="oe_edit_only" attrs="{'invisible': [('value_type','!=','codeable_concept')], 'required': [('value_type','=','codeable_concept')]}"/>
                                                                    <field name="value_attachment_id" class="oe_edit_only" attrs="{'invisible': [('value_type','!=','attachment')], 'required': [('value_type','=','attachment')]}"/>
                                                                    <field name="value_identifier_id" class="oe_edit_only" attrs="{'invisible': [('value_type','!=','identifier')], 'required': [('value_type','=','identifier')]}"/>
                                                                    <field name="value_quantity" class="oe_edit_only" attrs="{'invisible': [('value_type','!=','quantity')], 'required': [('value_type','=','quantity')]}"/>
                                                                    <field name="value_quantity_uom_id" class="oe_edit_only" attrs="{'invisible': [('value_type','!=','quantity')], 'required': [('value_type','=','quantity')]}"/>
                                                                    <field name="value_range" class="oe_edit_only" attrs="{'invisible': [('value_type','!=','range')], 'required': [('value_type','=','range')]}"/>
                                                                    <field name="value_period" class="oe_edit_only" attrs="{'invisible': [('value_type','!=','period')], 'required': [('value_type','=','period')]}"/>
                                                                    <field name="value_period_uom_id" class="oe_edit_only" attrs="{'invisible': [('value_type','!=','period')], 'required': [('value_type','=','period')]}"/>
                                                                    <field name="value_ratio" class="oe_edit_only" attrs="{'invisible': [('value_type','!=','ratio')], 'required': [('value_type','=','ratio')]}"/>
                                                                    <field name="value_human_name_id" class="oe_edit_only" attrs="{'invisible': [('value_type','!=','human_name')], 'required': [('value_type','=','human_name')]}"/>
                                                                    <field name="value_address_id" class="oe_edit_only" attrs="{'invisible': [('value_type','!=','address')], 'required': [('value_type','=','address')]}"/>
                                                                    <field name="value_contact_point_id" class="oe_edit_only" attrs="{'invisible': [('value_type','!=','contact_point')], 'required': [('value_type','=','contact_point')]}"/>
                                                                    <field name="value_timing_id" class="oe_edit_only" attrs="{'invisible': [('value_type','!=','timing')], 'required': [('value_type','=','timing')]}"/>
                                                                    <field name="value_signature_id" class="oe_edit_only" attrs="{'invisible': [('value_type','!=','signature')], 'required': [('value_type','=','signature')]}"/>
                                                                    <field name="value_reference_id" class="oe_edit_only" attrs="{'invisible': [('value_type','!=','reference')], 'required': [('value_type','=','reference')]}"/>
                                                                    <field name="value_time" class="oe_edit_only" attrs="{'invisible': [('value_type','!=','time')], 'required': [('value_type','=','time')]}"/>
                                                                    <field name="value_oid" class="oe_edit_only" attrs="{'invisible': [('value_type','!=','oid')], 'required': [('value_type','=','oid')]}"/>
                                                                    <field name="value_id" class="oe_edit_only" attrs="{'invisible': [('value_type','!=','id')], 'required': [('value_type','=','id')]}"/>
                                                                    <field name="value_unsigned_int" class="oe_edit_only" attrs="{'invisible': [('value_type','!=','unsigned_int')], 'required': [('value_type','=','unsigned_int')]}"/>
                                                                    <field name="value_positive_int" class="oe_edit_only" attrs="{'invisible': [('value_type','!=','positive_int')], 'required': [('value_type','=','positive_int')]}"/>
                                                                    <field name="value_annotation_id" class="oe_edit_only" attrs="{'invisible': [('value_type','!=','annotation')], 'required': [('value_type','=','annotation')]}"/>
                                                                    <field name="value_sampled_data_id" class="oe_edit_only" attrs="{'invisible': [('value_type','!=','sampled_data')], 'required': [('value_type','=','sampled_data')]}"/>
                                                                    <field name="value_meta_id" class="oe_edit_only" attrs="{'invisible': [('value_type','!=','meta')], 'required': [('value_type','=','meta')]}"/>
                                                                </group>
                                                                <group>
                                                                </group>
                                                            </group>
                                                        </sheet>
                                                    </form>
                                                </field>
                                            </page>
                                        </notebook>
                                    </sheet>
                                </form>
                            </page>
                        </notebook>
                    </sheet>
                </form>
            </field>
        </record>


        <act_window id="hc_res_organization_action"
                    name="HC Organizations"
                    res_model="hc.res.organization"
                    view_mode="tree,form"
                    domain=""
                    context=""
                    limit=""/>

        <menuitem id="hc_organization.menu_org"
                  name="Organizations"
                  web_icon="hc_organization,static/description/icon.png"
                  parent="hc_base.menu_entity"
                  action="hc_res_organization_action"
                  groups="hc_base.group_hc_base_manager"
                  sequence="10"/>

        <!-- Organization Type Views -->

        <record id="hc_vs_organization_type_view_search" model="ir.ui.view">
            <field name="name">Organization Type Search</field>
            <field name="model">hc.vs.organization.type</field>
            <field name="arch" type="xml">
                <search string="Organization Types">
                    <field name="name"/>
                    <field name="code"/>
                    <field name="definition"/>
                    <group>
                        <filter name="group_by_parent" string="parent" context="{'group_by': 'contains_id'}"/>
                    </group>
                </search>
            </field>
        </record>

        <record id="hc_vs_organization_type_view_tree" model="ir.ui.view">
            <field name="name">Organization Type Tree</field>
            <field name="model">hc.vs.organization.type</field>
            <field name="arch" type="xml">
                <tree string="Organization Types" default_order="name, code">
                    <field name="name"/>
                    <field name="code"/>
                    <field name="definition"/>
                    <field name="contains_id"/>
                    <field name="source_id" invisible="0"/>
                </tree>
            </field>
        </record>

        <record id="hc_vs_organization_type_view_form" model="ir.ui.view">
            <field name="name">Organization Type Form</field>
            <field name="model">hc.vs.organization.type</field>
            <field name="arch" type="xml">
                <form string="Organization Types">
                    <sheet>
                        <h1>
                            <field name="name" default_focus="1" placeholder="Name (e.g., Biological Substance)"/>
                        </h1>
                        <field name="code" placeholder="Code (e.g., biological)"/>
                        <field name="definition" placeholder="Definition"/>
                        <field name="comments" placeholder="Comments"/>
                        <group>
                            <group>
                                <field name="contains_id"/>
                            </group>
                            <group>
                                <field name="source_id" placeholder="e.g., U.S. Census Bureau"/>
                                <field name="system" widget="url" placeholder="e.g., www.census.gov/"/>
                            </group>
                        </group>
                    </sheet>
                </form>
            </field>
        </record>

        <act_window id="hc_vs_organization_type_action"
                    name="HC Organization Types"
                    res_model="hc.vs.organization.type"
                    view_mode="tree,form"
                    domain=""
                    context=""
                    limit=""/>

        <menuitem id="hc_organization.menu_org_type"
                  name="Organization Types"
                  parent="hc_organization.menu_org"
                  action="hc_vs_organization_type_action"
                  groups="hc_base.group_hc_base_manager"
                  sequence="10"/>

        <!-- Contact Entity Type Views -->

        <record id="hc_vs_contact_entity_type_view_search" model="ir.ui.view">
            <field name="name">Contact Entity Type Search</field>
            <field name="model">hc.vs.contact.entity.type</field>
            <field name="arch" type="xml">
                <search string="Contact Entity Types">
                    <field name="name"/>
                    <field name="code"/>
                    <field name="definition"/>
                    <group>
                        <filter name="group_by_parent" string="parent" context="{'group_by': 'contains_id'}"/>
                    </group>
                </search>
            </field>
        </record>

        <record id="hc_vs_contact_entity_type_view_tree" model="ir.ui.view">
            <field name="name">Contact Entity Type Tree</field>
            <field name="model">hc.vs.contact.entity.type</field>
            <field name="arch" type="xml">
                <tree string="Contact Entity Types" default_order="name, code">
                    <field name="name"/>
                    <field name="code"/>
                    <field name="definition"/>
                    <field name="contains_id"/>
                    <field name="source_id" invisible="0"/>
                </tree>
            </field>
        </record>

        <record id="hc_vs_contact_entity_type_view_form" model="ir.ui.view">
            <field name="name">Contact Entity Type Form</field>
            <field name="model">hc.vs.contact.entity.type</field>
            <field name="arch" type="xml">
                <form string="Contact Entity Types">
                    <sheet>
                        <h1>
                            <field name="name" default_focus="1" placeholder="Name (e.g., Biological Substance)"/>
                        </h1>
                        <field name="code" placeholder="Code (e.g., biological)"/>
                        <field name="definition" placeholder="Definition"/>
                        <field name="comments" placeholder="Comments"/>
                        <group>
                            <group>
                                <field name="contains_id"/>
                            </group>
                            <group>
                                <field name="source_id" placeholder="e.g., U.S. Census Bureau"/>
                                <field name="system" widget="url" placeholder="e.g., www.census.gov/"/>
                            </group>
                        </group>
                    </sheet>
                </form>
            </field>
        </record>

        <act_window id="hc_vs_contact_entity_type_action"
                    name="HC Contact Entity Types"
                    res_model="hc.vs.contact.entity.type"
                    view_mode="tree,form"
                    domain=""
                    context=""
                    limit=""/>

        <menuitem id="hc_organization.menu_cont_enty_type"
                  name="Contact Entity Types"
                  parent="hc_organization.menu_org"
                  action="hc_vs_contact_entity_type_action"
                  groups="hc_base.group_hc_base_manager"
                  sequence="20"/>

        <!-- External Reference -->

        <record id="hc_vs_identifier_code_view_form_inherited" model="ir.ui.view">
            <field name="name">Identifier Code Form Inherit</field>
            <field name="model">hc.vs.identifier.code</field>
            <field name="inherit_id" ref="hc_base.hc_vs_identifier_code_view_form"/>
            <field name="arch" type="xml">
                <xpath expr="//form//group//field[@name='type_id']" position="after">
                    <field name="assigner_id"/>
                </xpath>
            </field>
        </record>

<!--         <record id="hc_res_person_view_form_inherited_organization" model="ir.ui.view">
            <field name="name">Person Form</field>
            <field name="model">hc.res.person</field>
            <field name="inherit_id" ref="hc_person.hc_res_person_view_form"/>
            <field name="arch" type="xml">
                <xpath expr="//field[@name='is_active']" position="after">
                    <field name="is_organization_contact" readonly="1"/>
                </xpath>
                <xpath expr="//field[@name='target_person_id']" position="after">
                    <field name="target_organization_id" attrs="{'invisible': [('target_type','!=','organization')]}"/>
                    <field name="target_organization_contact_id" attrs="{'invisible': [('target_type','!=','organization_contact')]}"/>
                </xpath>
            </field>
        </record> -->

    </data>
</odoo>
