<odoo>
    <data>

        <!-- Narrative Views -->

        <record id="hc_narrative_view_search" model="ir.ui.view">
            <field name="name">Narrative Search</field>
            <field name="model">hc.narrative</field>
            <field name="arch" type="xml">
                <search string="Narratives">
                    <field name="title"/>
                    <field name="status"/>
                </search>
            </field>
        </record>

        <record id="hc_narrative_view_tree" model="ir.ui.view">
            <field name="name">Narrative Tree</field>
            <field name="model">hc.narrative</field>
            <field name="arch" type="xml">
                <tree string="Narratives">
                    <field name="title"/>
                    <field name="status"/>
                </tree>
            </field>
        </record>

        <record id="hc_narrative_view_form" model="ir.ui.view">
            <field name="name">Narrative Form</field>
            <field name="model">hc.narrative</field>
            <field name="arch" type="xml">
                <form string="Narrative">
                    <sheet>
                        <h1>
                            <field name="title" default_focus="1" placeholder="Title"/>
                        </h1>
                        <group>
                            <group>
                            </group>
                            <group>
                            </group>
                        </group>
                        <notebook>
                            <page string="Status History">
                                <field name="status_history_ids" mode="tree">
                                    <tree>
                                        <field name="status" readonly="1"/>
                                        <field name="start_date"/>
                                        <field name="end_date"/>
                                        <field name="time_diff_day"/>
                                        <field name="time_diff_hour"/>
                                        <field name="time_diff_min"/>
                                        <field name="time_diff_sec"/>
                                        <field name="write_uid" invisible="0"/>
                                    </tree>
                                </field>
                            </page>
                        </notebook>
                    </sheet>
                </form>
            </field>
        </record>

    </data>
</odoo>
