<odoo>
    <data noupdate="0">

        <!-- Snapshot -->

        <record id="ccda-care-plan-69" model="hc.structure.definition.snapshot">
            <field name="name">CDA on FHIR Care Plan Snapshot</field>
        </record>

        <!-- Differential -->

        <record id="ccda-care-plan-3363" model="hc.structure.definition.differential">
            <field name="name">CDA on FHIR Care Plan Differential</field>
        </record>

        <record id="ccda-care-plan-3364" model="hc.structure.definition.differential.element">  
            <field name="differential_id" ref="ccda-care-plan-3363"/>   
            <field name="identifier">Composition:c-cdaonfhircareplan</field>
            <field name="path">Composition</field>  
        </record>       
        
        <record id="ccda-care-plan-3367" model="hc.structure.definition.differential.element">  
            <field name="differential_id" ref="ccda-care-plan-3363"/>   
            <field name="identifier">Composition:c-cdaonfhircareplan.type</field>
            <field name="path">Composition.type</field> 
            <field name="label">Overall Plan of Care/Advance Care Directives</field>    
            <field name="short">Overall Plan of Care/Advance Care Directives</field>    
            <field name="definition">SHALL contain exactly one [1..1] type="52521-2" (CodeSystem: LOINC http://loinc.org STATIC) (CONF:2219-1498).</field>  
            <field name="min">1</field> 
            <field name="max">1</field> 
        </record>       
        
        <record id="ccda-care-plan-3385" model="hc.structure.definition.differential.element">  
            <field name="differential_id" ref="ccda-care-plan-3363"/>   
            <field name="identifier">Composition:c-cdaonfhircareplan.section</field>
            <field name="path">Composition.section</field>  
        </record>       
        
        <record id="ccda-care-plan-3394" model="hc.structure.definition.differential.element">  
            <field name="differential_id" ref="ccda-care-plan-3363"/>   
            <field name="identifier">Composition:c-cdaonfhircareplan.section:section_slice_pos2</field>
            <field name="path">Composition.section</field>  
            <field name="slice_name">section_slice_pos2</field>   
            <field name="label">Health Concerns Section</field> 
            <field name="short">Health Concerns Section</field> 
            <field name="definition">SHALL contain exactly one [1..1] section (CONF:2219-1393) such that it</field> 
            <field name="comment">Health Concerns Section</field>  
            <field name="min">1</field> 
            <field name="max">1</field> 
        </record>

        <record id="ccda-care-plan-3405" model="hc.structure.definition.differential.element">  
            <field name="differential_id" ref="ccda-care-plan-3363"/>   
            <field name="identifier">Composition:c-cdaonfhircareplan.section:section_slice_pos2.title:section_slice_pos2</field>
            <field name="path">Composition.section.title</field>    
            <field name="slice_name">section_slice_pos2</field>   
            <field name="short">title</field>   
            <field name="definition">SHALL contain exactly one [1..1] title (CONF:2219-1420).</field>   
            <field name="min">1</field> 
            <field name="max">1</field> 
        </record>       
        
        <record id="ccda-care-plan-3415" model="hc.structure.definition.differential.element">  
            <field name="differential_id" ref="ccda-care-plan-3363"/>   
            <field name="identifier">Composition:c-cdaonfhircareplan.section:section_slice_pos2.code:section_slice_pos2</field>
            <field name="path">Composition.section.code</field> 
            <field name="slice_name">section_slice_pos2</field>   
            <field name="label">Health concerns document</field>    
            <field name="short">Health concerns document</field>    
            <field name="definition">SHALL contain exactly one [1..1] code="75310-3" (CodeSystem: LOINC http://loinc.org) (CONF:2219-1421).</field> 
            <field name="min">1</field> 
            <field name="max">1</field> 
        </record>       
        
        <record id="ccda-care-plan-3435" model="hc.structure.definition.differential.element">  
            <field name="differential_id" ref="ccda-care-plan-3363"/>   
            <field name="identifier">Composition:c-cdaonfhircareplan.section:section_slice_pos2.text:section_slice_pos2</field>
            <field name="path">Composition.section.text</field> 
            <field name="slice_name">section_slice_pos2</field>   
            <field name="short">text</field>    
            <field name="definition">SHALL contain exactly one [1..1] text (CONF:2219-1422).</field>    
            <field name="min">1</field> 
            <field name="max">1</field> 
        </record>       
        
        <record id="ccda-care-plan-3445" model="hc.structure.definition.differential.element">  
            <field name="differential_id" ref="ccda-care-plan-3363"/>   
            <field name="identifier">Composition:c-cdaonfhircareplan.section:section_slice_pos3</field>
            <field name="path">Composition.section</field>  
            <field name="slice_name">section_slice_pos3</field>   
            <field name="label">Goals Section</field>   
            <field name="short">Goals Section</field>   
            <field name="definition">SHALL contain exactly one [1..1] section (CodeSystem: LOINC http://loinc.org) (CONF:2219-1394) such that it</field>    
            <field name="comment">Goals Section</field>    
            <field name="min">1</field> 
            <field name="max">1</field> 
        </record>       
        
        <record id="ccda-care-plan-3456" model="hc.structure.definition.differential.element">  
            <field name="differential_id" ref="ccda-care-plan-3363"/>   
            <field name="identifier">Composition:c-cdaonfhircareplan.section:section_slice_pos3.title:section_slice_pos3</field>
            <field name="path">Composition.section.title</field>    
            <field name="slice_name">section_slice_pos3</field>   
            <field name="label">Hospital course</field> 
            <field name="short">Hospital course</field> 
            <field name="definition">SHALL contain exactly one [1..1] title (CONF:2219-1423).</field>   
            <field name="min">1</field> 
            <field name="max">1</field> 
        </record>       
        
        <record id="ccda-care-plan-3467" model="hc.structure.definition.differential.element">  
            <field name="differential_id" ref="ccda-care-plan-3363"/>   
            <field name="identifier">Composition:c-cdaonfhircareplan.section:section_slice_pos3.code:section_slice_pos3</field>
            <field name="path">Composition.section.code</field> 
            <field name="slice_name">section_slice_pos3</field>   
            <field name="label">Goals</field>   
            <field name="short">Goals</field>   
            <field name="definition">SHALL contain exactly one [1..1] code="61146-7" (CodeSystem: LOINC http://loinc.org) (CONF:2219-1424).</field> 
            <field name="min">1</field> 
            <field name="max">1</field> 
        </record>       
        
        <record id="ccda-care-plan-3487" model="hc.structure.definition.differential.element">  
            <field name="differential_id" ref="ccda-care-plan-3363"/>   
            <field name="identifier">Composition:c-cdaonfhircareplan.section:section_slice_pos3.text:section_slice_pos3</field>
            <field name="path">Composition.section.text</field> 
            <field name="slice_name">section_slice_pos3</field>   
            <field name="short">text</field>    
            <field name="definition">SHALL contain exactly one [1..1] text (CONF:2219-1425).</field>    
            <field name="min">1</field> 
            <field name="max">1</field> 
        </record>       
        
        <record id="ccda-care-plan-3497" model="hc.structure.definition.differential.element">  
            <field name="differential_id" ref="ccda-care-plan-3363"/>   
            <field name="identifier">Composition:c-cdaonfhircareplan.section:section_slice_pos4</field>
            <field name="path">Composition.section</field>  
            <field name="slice_name">section_slice_pos4</field>   
            <field name="label">Interventions Section</field>   
            <field name="short">Interventions Section</field>   
            <field name="definition">SHOULD contain zero or one [0..1] section (CONF:2219-1395) such that it</field>    
            <field name="comment">Interventions Section</field>    
            <field name="min">0</field> 
            <field name="max">1</field> 
        </record>       
        
        <record id="ccda-care-plan-3508" model="hc.structure.definition.differential.element">  
            <field name="differential_id" ref="ccda-care-plan-3363"/>   
            <field name="identifier">Composition:c-cdaonfhircareplan.section:section_slice_pos4.title:section_slice_pos4</field>
            <field name="path">Composition.section.title</field>    
            <field name="slice_name">section_slice_pos4</field>   
            <field name="short">title</field>   
            <field name="definition">SHALL contain exactly one [1..1] title (CONF:2219-1426).</field>   
            <field name="min">1</field> 
            <field name="max">1</field> 
        </record>       
        
        <record id="ccda-care-plan-3518" model="hc.structure.definition.differential.element">  
            <field name="differential_id" ref="ccda-care-plan-3363"/>   
            <field name="identifier">Composition:c-cdaonfhircareplan.section:section_slice_pos4.code:section_slice_pos4</field>
            <field name="path">Composition.section.code</field> 
            <field name="slice_name">section_slice_pos4</field>   
            <field name="label">Interventions provided</field>  
            <field name="short">Interventions provided</field>  
            <field name="definition">SHALL contain exactly one [1..1] code="62387-6" (CodeSystem: LOINC http://loinc.org) (CONF:2219-1427).</field> 
            <field name="min">1</field> 
            <field name="max">1</field> 
        </record>       
        
        <record id="ccda-care-plan-3538" model="hc.structure.definition.differential.element">  
            <field name="differential_id" ref="ccda-care-plan-3363"/>   
            <field name="identifier">Composition:c-cdaonfhircareplan.section:section_slice_pos4.text:section_slice_pos4</field>
            <field name="path">Composition.section.text</field> 
            <field name="slice_name">section_slice_pos4</field>   
            <field name="short">text</field>    
            <field name="definition">SHALL contain exactly one [1..1] text (CONF:2219-1428).</field>    
            <field name="min">1</field> 
            <field name="max">1</field> 
        </record>       
        
        <record id="ccda-care-plan-3548" model="hc.structure.definition.differential.element">  
            <field name="differential_id" ref="ccda-care-plan-3363"/>   
            <field name="identifier">Composition:c-cdaonfhircareplan.section:section_slice_pos5</field>
            <field name="path">Composition.section</field>  
            <field name="slice_name">section_slice_pos5</field>   
            <field name="label">Health Status Evaluations and Outcomes Section</field>  
            <field name="short">Health Status Evaluations and Outcomes Section</field>  
            <field name="definition">SHOULD contain zero or one [0..1] section (CONF:2219-1414) such that it</field>    
            <field name="comment">Health Status Evaluations and Outcomes Section</field>   
            <field name="min">0</field> 
            <field name="max">1</field> 
        </record>       
        
        <record id="ccda-care-plan-3559" model="hc.structure.definition.differential.element">  
            <field name="differential_id" ref="ccda-care-plan-3363"/>   
            <field name="identifier">Composition:c-cdaonfhircareplan.section:section_slice_pos5.title:section_slice_pos5</field>
            <field name="path">Composition.section.title</field>    
            <field name="slice_name">section_slice_pos5</field>   
            <field name="short">title</field>   
            <field name="definition">SHALL contain exactly one [1..1] title (CONF:2219-1483).</field>   
            <field name="min">1</field> 
            <field name="max">1</field> 
        </record>       
        
        <record id="ccda-care-plan-3569" model="hc.structure.definition.differential.element">  
            <field name="differential_id" ref="ccda-care-plan-3363"/>   
            <field name="identifier">Composition:c-cdaonfhircareplan.section:section_slice_pos5.code:section_slice_pos5</field>
            <field name="path">Composition.section.code</field> 
            <field name="slice_name">section_slice_pos5</field>   
            <field name="label">Patient problem outcome</field> 
            <field name="short">Patient problem outcome</field> 
            <field name="definition">SHALL contain exactly one [1..1] code="11383-7" (CodeSystem: LOINC http://loinc.org) (CONF:2219-1484).</field> 
            <field name="min">1</field> 
            <field name="max">1</field> 
        </record>       
        
        <record id="ccda-care-plan-3589" model="hc.structure.definition.differential.element">  
            <field name="differential_id" ref="ccda-care-plan-3363"/>   
            <field name="identifier">Composition:c-cdaonfhircareplan.section:section_slice_pos5.text:section_slice_pos5</field>
            <field name="path">Composition.section.text</field> 
            <field name="slice_name">section_slice_pos5</field>   
            <field name="short">text</field>    
            <field name="definition">SHALL contain exactly one [1..1] text (CONF:2219-1485).</field>    
            <field name="min">1</field> 
            <field name="max">1</field> 
        </record>       
       
        <!-- Care Plan Composition -->

        <record id="ccda-care-plan-composition" model="hc.res.structure.definition">    
            <field name="url">http://hl7.org/fhir/ccda/StructureDefinition/ccda-care-plan-composition</field>
            <field name="name">C-CDA on FHIR Care Plan</field>
            <field name="status">draft</field>
            <field name="publisher">Lantana Consulting Group</field>
            <field name="date">2016-08-11T00:38:46+10:00</field>
            <field name="description">CARE PLAN FRAMEWORK: Care Plan (including Home Health Plan of Care (HHPoC)) is a consensus-driven dynamic plan that represents a patient&apos;s and Care Team Members&apos; prioritized concerns, goals, and planned interventions. It serves as a blueprint shared by all Care Team Members (including the patient, their caregivers and providers), to guide the patient’s care. A Care Plan integrates multiple interventions proposed by multiple providers and disciplines for multiple conditions.&#10;&#10;A Care Plan represents one or more Plan(s) of Care and serves to reconcile and resolve conflicts between the various Plans of Care developed for a specific patient by different providers. While both a plan of care and a care plan include the patient&apos;s life goals and require Care Team Members (including patients) to prioritize goals and interventions, the reconciliation process becomes more complex as the number of plans of care increases. The Care Plan also serves to enable longitudinal coordination of care.&#10;&#10;The Care Plan represents an instance of this dynamic Care Plan at a point in time. The composition itself is NOT dynamic.&#10;&#10;Key differentiators between a Care Plan profile and CCD  profile (another &quot;snapshot in time&quot; document):&#10;
            •  Requires relationships between various acts:
                    o  Health Concerns
                    o  Problems
                    o  Interventions
                    o  Goals
                    o  Outcomes&#10;
            •  Provides the ability to identify patient and provider priorities with each act
            •  Provides a header participant to indicate occurrences of Care Plan review</field>
            <field name="kind">resource</field>
            <field name="abstract">false</field>
            <field name="type">composition</field>
            <field name="base_definition">http://hl7.org/fhir/ccda/StructureDefinition/ccda-us-realm-header-composition</field>
            <field name="derivation">constraint</field>
            <field name="snapshot_id" ref="ccda-care-plan-69"/>
            <field name="differential_id" ref="ccda-care-plan-3363"/>
        </record>

        <record id="hc_base.ident_code_struc_defn" model="hc.vs.identifier.code">
            <field name="code">fhir_structure_definition</field>
            <field name="name">FHIR Structure Definition</field>
            <field name="type_id" ref="hc_base.ident_ri"/>
        </record>

        <record id="ccda-care-plan-15" model="hc.structure.definition.identifier">
            <field name="structure_definition_id" ref="ccda-care-plan-composition"/>
            <field name="value">ccda-care-plan-composition</field>
            <field name="code_id" ref="hc_base.ident_code_struc_defn"/>  
        </record> 

        <!-- Contacts -->

        <record id="hc_base.cont_pt_5" model="hc.contact.point">    
            <field name="system">phone</field>
            <field name="value">+6 141-029-2506</field>
        </record>

        <record id="hc_base.cont_pt_6" model="hc.contact.point">    
            <field name="system">email</field>
            <field name="value">sarah.gaunt@lantanagroup.com</field>
        </record>

        <record id="hc_base.ccda_care_plan_10" model="hc.contact.detail">   
            <field name="name">Sarah Gaunt</field>
        </record>   

        <record id="ccda-care-plan-12" model="hc.contact.detail.telecom">
            <field name="telecom_id" ref="hc_base.cont_pt_5"/>
            <field name="contact_detail_id" ref="hc_base.ccda_care_plan_10"/>   
            <field name="use">work</field>
        </record>   
        
        <record id="ccda-care-plan-17" model="hc.contact.detail.telecom">
            <field name="telecom_id" ref="hc_base.cont_pt_6"/>
            <field name="contact_detail_id" ref="hc_base.ccda_care_plan_10"/>   
            <field name="use">work</field>
        </record>

        <record id="hc_base" model="hc.structure.definition.contact">
            <field name="structure_definition_id" ref="ccda-care-plan-composition"/>
            <field name="contact_id" ref="hc_base.ccda_care_plan_10"/>   
        </record> 

        <!-- Mappings -->

        <record id="ccda-care-plan-48" model="hc.structure.definition.mapping">
            <field name="structure_definition_id" ref="ccda-care-plan-composition"/> 
            <field name="identity">rim</field>
            <field name="uri">http://hl7.org/v3</field>
            <field name="name">RIM Mapping</field>
        </record>   
        
        <record id="ccda-care-plan-53" model="hc.structure.definition.mapping">
            <field name="structure_definition_id" ref="ccda-care-plan-composition"/> 
            <field name="identity">cda</field>
            <field name="uri">http://hl7.org/v3/cda</field>
            <field name="name">CDA (R2)</field>
        </record>   
        
        <record id="ccda-care-plan-58" model="hc.structure.definition.mapping">
            <field name="structure_definition_id" ref="ccda-care-plan-composition"/> 
            <field name="identity">w5</field>
            <field name="uri">http://hl7.org/fhir/w5</field>
            <field name="name">W5 Mapping</field>
        </record>   



    </data>
</odoo>