<odoo>
    <data>

        <!-- Healthcare Service Views -->

        <record id="hc_res_healthcare_service_view_search" model="ir.ui.view">
            <field name="name">Healthcare Service Search</field>
            <field name="model">hc.res.healthcare.service</field>
            <field name="arch" type="xml">
                <search string="Healthcare Services">
                    <field name="name"/>
                    <field name="provided_by_id"/>
                    <field name="service_category_id"/>
                </search>
            </field>
        </record>

        <record id="hc_res_healthcare_service_view_tree" model="ir.ui.view">
            <field name="name">Healthcare Service Tree</field>
            <field name="model">hc.res.healthcare.service</field>
            <field name="arch" type="xml">
                <tree string="Healthcare Services">
                    <field name="name"/>
                    <field name="provided_by_id"/>
                    <field name="service_category_id"/>
                </tree>
            </field>
        </record>

        <record id="hc_res_healthcare_service_view_form" model="ir.ui.view">
            <field name="name">Healthcare Service Form</field>
            <field name="model">hc.res.healthcare.service</field>
            <field name="arch" type="xml">
                <form string="Healthcare Service">
                    <sheet>
                        <div>
                            <h1>
                                <field name="name" default_focus="1" placeholder="Name"/>
                            </h1>
                            <label for="comment" string="Comment"/>
                            <field name="comment"/>
                            <label for="extra_details" string="Extra Details"/>
                            <field name="extra_details"/>
                            <label for="availability_exceptions" string="Availability Exceptions"/>
                            <field name="availability_exceptions"/>
                        </div>
                        <group>
                            <group string="Characteristics">
                                <field name="is_active"/>
                                <field name="photo_id"/>
                                <field name="provided_by_id"/>
                                <field name="service_category_id"/>
                                <field name="type_ids" widget="many2many_tags"/>
                                <field name="specialty_ids" widget="many2many_tags"/>
                                <field name="service_provision_code_ids" widget="many2many_tags"/>
                                <field name="characteristic_ids" widget="many2many_tags"/>
                            </group>
                            <group string="Eligibility/Referral">
                                <field name="eligibility_id"/>
                                <field name="eligibility_note"/>
                                <field name="referral_method_ids" widget="many2many_tags"/>
                                <field name="is_appointment_required"/>
                            </group>
                        </group>
                        <notebook>
                            <page string="Identifiers">
                                <field name="identifier_ids" mode="tree">
                                    <tree>
                                        <field name="is_preferred"/>
                                        <field name="name"/>
                                        <field name="type_id"/>
                                        <field name="start_date"/>
                                        <field name="end_date"/>
                                    </tree>
                                    <form>
                                        <sheet>
                                            <div>
                                                <h1>
                                                    <field name="name" placeholder="Identifier"/>
                                                </h1>
                                            </div>
                                            <group col="4" colspan="4">
                                                <group>
                                                    <field name="value"/>
                                                    <field name="system"/>
                                                    <field name="code_id"/>
                                                    <field name="type_id"/>
                                                    <field name="use"/>
                                                </group>
                                                <group string="Association">
                                                    <field name="is_preferred"/>
                                                    <field name="is_active"/>
                                                    <field name="start_date" placeholder="Valid From"/>
                                                    <field name="end_date" placeholder="Valid To"/>
                                               </group>
                                            </group>
                                        </sheet>
                                    </form>
                                </field>
                            </page>
                            <page string="Locations">
                                <field name="location_ids" mode="tree">
                                    <tree>
                                        <field name="is_preferred"/>
                                        <field name="location_id"/>
                                        <field name="is_active"/>
                                        <field name="start_date"/>
                                        <field name="end_date"/>
                                    </tree>
                                    <form>
                                        <sheet>
                                            <group>
                                                <group>
                                                    <field name="location_id"/>
                                                </group>
                                                <group string="Association">
                                                    <field name="is_preferred"/>
                                                    <field name="is_active"/>
                                                    <field name="start_date" placeholder="Valid From"/>
                                                    <field name="end_date" placeholder="Valid To"/>
                                               </group>
                                            </group>
                                        </sheet>
                                    </form>
                                </field>
                            </page>
                            <page string="Telecoms">
                                <field name="telecom_ids" mode="tree">
                                    <tree>
                                        <field name="is_preferred"/>
                                        <field name="telecom_id"/>
                                        <field name="use"/>
                                    </tree>
                                    <form>
                                        <sheet>
                                            <group>
                                                <group>
                                                    <field name="telecom_id"/>
                                                    <field name="use"/>
                                                </group>
                                                <group string="Association">
                                                    <field name="is_preferred"/>
                                                    <field name="is_active"/>
                                                    <field name="start_date" placeholder="Valid From"/>
                                                    <field name="end_date" placeholder="Valid To"/>
                                               </group>
                                            </group>
                                        </sheet>
                                    </form>
                                </field>
                            </page>
                            <page string="Coverage Areas">
                                <field name="coverage_area_ids" mode="tree">
                                     <tree>
                                        <field name="is_preferred"/>
                                        <field name="location_id"/>
                                        <field name="is_active"/>
                                        <field name="start_date"/>
                                        <field name="end_date"/>
                                    </tree>
                                    <form>
                                        <sheet>
                                            <group>
                                                <group>
                                                    <field name="location_id"/>
                                                </group>
                                                <group string="Association">
                                                    <field name="is_preferred"/>
                                                    <field name="is_active"/>
                                                    <field name="start_date" placeholder="Valid From"/>
                                                    <field name="end_date" placeholder="Valid To"/>
                                               </group>
                                            </group>
                                        </sheet>
                                    </form>
                                </field>
                            </page>
                            <page string="Program Names">
                                <field name="program_name_ids" mode="tree">
                                    <tree>
                                        <field name="is_preferred"/>
                                        <field name="name"/>
                                        <field name="is_active"/>
                                        <field name="start_date"/>
                                        <field name="end_date"/>
                                    </tree>
                                    <form>
                                        <sheet>
                                            <group>
                                                <group>
                                                    <field name="name"/>
                                                </group>
                                                <group string="Association">
                                                    <field name="is_preferred"/>
                                                    <field name="is_active"/>
                                                    <field name="start_date" placeholder="Valid From"/>
                                                    <field name="end_date" placeholder="Valid To"/>
                                                </group>
                                            </group>
                                        </sheet>
                                    </form>
                                </field>
                            </page>
                            <page string="Available Times">
                                <field name="available_time_ids" mode="tree">
                                    <tree string="Available Times">
                                        <field name="is_all_day"/>
                                        <field name="available_start_time"/>
                                        <field name="available_end_time"/>
                                        <field name="days_of_week_ids" widget="many2many_tags"/>
                                    </tree>
                                    <form>
                                        <sheet>
                                            <group>
                                                <group>
                                                    <field name="is_all_day"/>
                                                    <field name="available_start_time"/>
                                                    <field name="available_end_time"/>
                                                    <field name="days_of_week_ids" widget="many2many_tags"/>
                                                </group>
                                                <group>
                                                </group>
                                            </group>
                                        </sheet>
                                    </form>
                                </field>
                            </page>
                            <page string="Not Available Times">
                                <field name="not_available_ids" mode="tree">
                                    <tree>
                                        <field name="description"/>
                                        <field name="during_start_date"/>
                                        <field name="during_end_date"/>
                                    </tree>
                                    <form>
                                        <sheet>
                                            <group>
                                                <group>
                                                    <field name="description"/>
                                                    <field name="during_start_date"/>
                                                    <field name="during_end_date"/>
                                                </group>
                                                <group>
                                                </group>
                                            </group>
                                        </sheet>
                                    </form>
                                </field>
                            </page>
                            <page string="Endpoints">
                                <field name="endpoint_ids" mode="tree">
                                    <tree>
                                        <field name="is_preferred"/>
                                        <field name="endpoint_id"/>
                                        <field name="is_active"/>
                                        <field name="start_date"/>
                                        <field name="end_date"/>
                                    </tree>
                                    <form>
                                        <sheet>
                                            <group>
                                                <group>
                                                    <field name="endpoint_id"/>
                                                </group>
                                                <group string="Association">
                                                    <field name="is_preferred"/>
                                                    <field name="is_active"/>
                                                    <field name="start_date" placeholder="Valid From"/>
                                                    <field name="end_date" placeholder="Valid To"/>
                                               </group>
                                            </group>
                                        </sheet>
                                    </form>
                                </field>
                            </page>
                            <page string="Meta">
                                <form>
                                    <sheet>
                                        <group string="Resource">
                                            <group>
                                                <field name="identifier"/>
                                                <field name="implicit_rules"/>
                                                <field name="language_id"/>
                                                <field name="meta_id"/>
                                            </group>
                                            <group>
                                            </group>
                                        </group>
                                        <group string="Domain Resource">
                                            <group>
                                                <field name="text_id"/>
                                            </group>
                                            <group>
                                            </group>
                                        </group>
                                        <notebook>
                                            <page string="Contained">
                                                <field name="contained_ids" mode="tree">
                                                    <tree>
                                                        <field name="identifier"/>
                                                        <field name="meta_id"/>
                                                        <field name="implicit_rules"/>
                                                        <field name="language_id"/>
                                                    </tree>
                                                    <form>
                                                        <sheet>
                                                            <group>
                                                                <group>
                                                                    <field name="identifier"/>
                                                                    <field name="meta_id"/>
                                                                    <field name="implicit_rules"/>
                                                                    <field name="language_id"/>
                                                                </group>
                                                                <group>
                                                                </group>
                                                            </group>
                                                        </sheet>
                                                    </form>
                                                </field>
                                            </page>
                                            <page string="Extensions">
                                                <field name="extension_ids" mode="tree">
                                                    <tree>
                                                        <field name="url"/>
                                                        <field name="value_name"/>
                                                        <field name="value_type"/>
                                                    </tree>
                                                    <form>
                                                        <sheet>
                                                            <group>
                                                                <group>
                                                                    <field name="url"/>
                                                                    <field name="value_name"/>
                                                                    <field name="value_type" class="oe_edit_only"/>
                                                                    <field name="value_integer" class="oe_edit_only" attrs="{'invisible': [('value_type','!=','integer')], 'required': [('value_type','=','integer')]}"/>
                                                                    <field name="value_decimal" class="oe_edit_only" attrs="{'invisible': [('value_type','!=','decimal')], 'required': [('value_type','=','decimal')]}"/>
                                                                    <field name="value_date_time" class="oe_edit_only" attrs="{'invisible': [('value_type','!=','date_time')], 'required': [('value_type','=','date_time')]}"/>
                                                                    <field name="value_date" class="oe_edit_only" attrs="{'invisible': [('value_type','!=','date')], 'required': [('value_type','=','date')]}"/>
                                                                    <field name="value_instant" class="oe_edit_only" attrs="{'invisible': [('value_type','!=','instant')], 'required': [('value_type','=','instant')]}"/>
                                                                    <field name="value_string" class="oe_edit_only" attrs="{'invisible': [('value_type','!=','string')], 'required': [('value_type','=','string')]}"/>
                                                                    <field name="value_uri" class="oe_edit_only" attrs="{'invisible': [('value_type','!=','uri')], 'required': [('value_type','=','uri')]}"/>
                                                                    <field name="value_boolean" class="oe_edit_only" attrs="{'invisible': [('value_type','!=','boolean')], 'required': [('value_type','=','boolean')]}"/>
                                                                    <field name="value_code_id" class="oe_edit_only" attrs="{'invisible': [('value_type','!=','code')], 'required': [('value_type','=','code')]}"/>
                                                                    <field name="value_markdown" class="oe_edit_only" attrs="{'invisible': [('value_type','!=','markdown')], 'required': [('value_type','=','markdown')]}"/>
                                                                    <field name="value_base_64_binary" class="oe_edit_only" attrs="{'invisible': [('value_type','!=','base_64_binary')], 'required': [('value_type','=','base_64_binary')]}"/>
                                                                    <field name="value_coding_id" class="oe_edit_only" attrs="{'invisible': [('value_type','!=','coding')], 'required': [('value_type','=','coding')]}"/>
                                                                    <field name="value_codeable_concept_id" class="oe_edit_only" attrs="{'invisible': [('value_type','!=','codeable_concept')], 'required': [('value_type','=','codeable_concept')]}"/>
                                                                    <field name="value_attachment_id" class="oe_edit_only" attrs="{'invisible': [('value_type','!=','attachment')], 'required': [('value_type','=','attachment')]}"/>
                                                                    <field name="value_identifier_id" class="oe_edit_only" attrs="{'invisible': [('value_type','!=','identifier')], 'required': [('value_type','=','identifier')]}"/>
                                                                    <field name="value_quantity" class="oe_edit_only" attrs="{'invisible': [('value_type','!=','quantity')], 'required': [('value_type','=','quantity')]}"/>
                                                                    <field name="value_quantity_uom_id" class="oe_edit_only" attrs="{'invisible': [('value_type','!=','quantity')], 'required': [('value_type','=','quantity')]}"/>
                                                                    <field name="value_range" class="oe_edit_only" attrs="{'invisible': [('value_type','!=','range')], 'required': [('value_type','=','range')]}"/>
                                                                    <field name="value_period" class="oe_edit_only" attrs="{'invisible': [('value_type','!=','period')], 'required': [('value_type','=','period')]}"/>
                                                                    <field name="value_period_uom_id" class="oe_edit_only" attrs="{'invisible': [('value_type','!=','period')], 'required': [('value_type','=','period')]}"/>
                                                                    <field name="value_ratio" class="oe_edit_only" attrs="{'invisible': [('value_type','!=','ratio')], 'required': [('value_type','=','ratio')]}"/>
                                                                    <field name="value_human_name_id" class="oe_edit_only" attrs="{'invisible': [('value_type','!=','human_name')], 'required': [('value_type','=','human_name')]}"/>
                                                                    <field name="value_address_id" class="oe_edit_only" attrs="{'invisible': [('value_type','!=','address')], 'required': [('value_type','=','address')]}"/>
                                                                    <field name="value_contact_point_id" class="oe_edit_only" attrs="{'invisible': [('value_type','!=','contact_point')], 'required': [('value_type','=','contact_point')]}"/>
                                                                    <field name="value_timing_id" class="oe_edit_only" attrs="{'invisible': [('value_type','!=','timing')], 'required': [('value_type','=','timing')]}"/>
                                                                    <field name="value_signature_id" class="oe_edit_only" attrs="{'invisible': [('value_type','!=','signature')], 'required': [('value_type','=','signature')]}"/>
                                                                    <field name="value_reference_id" class="oe_edit_only" attrs="{'invisible': [('value_type','!=','reference')], 'required': [('value_type','=','reference')]}"/>
                                                                    <field name="value_time" class="oe_edit_only" attrs="{'invisible': [('value_type','!=','time')], 'required': [('value_type','=','time')]}"/>
                                                                    <field name="value_oid" class="oe_edit_only" attrs="{'invisible': [('value_type','!=','oid')], 'required': [('value_type','=','oid')]}"/>
                                                                    <field name="value_id" class="oe_edit_only" attrs="{'invisible': [('value_type','!=','id')], 'required': [('value_type','=','id')]}"/>
                                                                    <field name="value_unsigned_int" class="oe_edit_only" attrs="{'invisible': [('value_type','!=','unsigned_int')], 'required': [('value_type','=','unsigned_int')]}"/>
                                                                    <field name="value_positive_int" class="oe_edit_only" attrs="{'invisible': [('value_type','!=','positive_int')], 'required': [('value_type','=','positive_int')]}"/>
                                                                    <field name="value_annotation_id" class="oe_edit_only" attrs="{'invisible': [('value_type','!=','annotation')], 'required': [('value_type','=','annotation')]}"/>
                                                                    <field name="value_sampled_data_id" class="oe_edit_only" attrs="{'invisible': [('value_type','!=','sampled_data')], 'required': [('value_type','=','sampled_data')]}"/>
                                                                    <field name="value_meta_id" class="oe_edit_only" attrs="{'invisible': [('value_type','!=','meta')], 'required': [('value_type','=','meta')]}"/>
                                                                </group>
                                                                <group>
                                                                </group>
                                                            </group>
                                                        </sheet>
                                                    </form>
                                                </field>
                                            </page>
                                            <page string="Modifier Extensions">
                                                <field name="modifier_extension_ids" mode="tree">
                                                    <tree>
                                                        <field name="url"/>
                                                        <field name="value_name"/>
                                                        <field name="value_type"/>
                                                    </tree>
                                                    <form>
                                                        <sheet>
                                                            <group>
                                                                <group>
                                                                    <field name="url"/>
                                                                    <field name="value_name"/>
                                                                    <field name="value_type" class="oe_edit_only"/>
                                                                    <field name="value_integer" class="oe_edit_only" attrs="{'invisible': [('value_type','!=','integer')], 'required': [('value_type','=','integer')]}"/>
                                                                    <field name="value_decimal" class="oe_edit_only" attrs="{'invisible': [('value_type','!=','decimal')], 'required': [('value_type','=','decimal')]}"/>
                                                                    <field name="value_date_time" class="oe_edit_only" attrs="{'invisible': [('value_type','!=','date_time')], 'required': [('value_type','=','date_time')]}"/>
                                                                    <field name="value_date" class="oe_edit_only" attrs="{'invisible': [('value_type','!=','date')], 'required': [('value_type','=','date')]}"/>
                                                                    <field name="value_instant" class="oe_edit_only" attrs="{'invisible': [('value_type','!=','instant')], 'required': [('value_type','=','instant')]}"/>
                                                                    <field name="value_string" class="oe_edit_only" attrs="{'invisible': [('value_type','!=','string')], 'required': [('value_type','=','string')]}"/>
                                                                    <field name="value_uri" class="oe_edit_only" attrs="{'invisible': [('value_type','!=','uri')], 'required': [('value_type','=','uri')]}"/>
                                                                    <field name="value_boolean" class="oe_edit_only" attrs="{'invisible': [('value_type','!=','boolean')], 'required': [('value_type','=','boolean')]}"/>
                                                                    <field name="value_code_id" class="oe_edit_only" attrs="{'invisible': [('value_type','!=','code')], 'required': [('value_type','=','code')]}"/>
                                                                    <field name="value_markdown" class="oe_edit_only" attrs="{'invisible': [('value_type','!=','markdown')], 'required': [('value_type','=','markdown')]}"/>
                                                                    <field name="value_base_64_binary" class="oe_edit_only" attrs="{'invisible': [('value_type','!=','base_64_binary')], 'required': [('value_type','=','base_64_binary')]}"/>
                                                                    <field name="value_coding_id" class="oe_edit_only" attrs="{'invisible': [('value_type','!=','coding')], 'required': [('value_type','=','coding')]}"/>
                                                                    <field name="value_codeable_concept_id" class="oe_edit_only" attrs="{'invisible': [('value_type','!=','codeable_concept')], 'required': [('value_type','=','codeable_concept')]}"/>
                                                                    <field name="value_attachment_id" class="oe_edit_only" attrs="{'invisible': [('value_type','!=','attachment')], 'required': [('value_type','=','attachment')]}"/>
                                                                    <field name="value_identifier_id" class="oe_edit_only" attrs="{'invisible': [('value_type','!=','identifier')], 'required': [('value_type','=','identifier')]}"/>
                                                                    <field name="value_quantity" class="oe_edit_only" attrs="{'invisible': [('value_type','!=','quantity')], 'required': [('value_type','=','quantity')]}"/>
                                                                    <field name="value_quantity_uom_id" class="oe_edit_only" attrs="{'invisible': [('value_type','!=','quantity')], 'required': [('value_type','=','quantity')]}"/>
                                                                    <field name="value_range" class="oe_edit_only" attrs="{'invisible': [('value_type','!=','range')], 'required': [('value_type','=','range')]}"/>
                                                                    <field name="value_period" class="oe_edit_only" attrs="{'invisible': [('value_type','!=','period')], 'required': [('value_type','=','period')]}"/>
                                                                    <field name="value_period_uom_id" class="oe_edit_only" attrs="{'invisible': [('value_type','!=','period')], 'required': [('value_type','=','period')]}"/>
                                                                    <field name="value_ratio" class="oe_edit_only" attrs="{'invisible': [('value_type','!=','ratio')], 'required': [('value_type','=','ratio')]}"/>
                                                                    <field name="value_human_name_id" class="oe_edit_only" attrs="{'invisible': [('value_type','!=','human_name')], 'required': [('value_type','=','human_name')]}"/>
                                                                    <field name="value_address_id" class="oe_edit_only" attrs="{'invisible': [('value_type','!=','address')], 'required': [('value_type','=','address')]}"/>
                                                                    <field name="value_contact_point_id" class="oe_edit_only" attrs="{'invisible': [('value_type','!=','contact_point')], 'required': [('value_type','=','contact_point')]}"/>
                                                                    <field name="value_timing_id" class="oe_edit_only" attrs="{'invisible': [('value_type','!=','timing')], 'required': [('value_type','=','timing')]}"/>
                                                                    <field name="value_signature_id" class="oe_edit_only" attrs="{'invisible': [('value_type','!=','signature')], 'required': [('value_type','=','signature')]}"/>
                                                                    <field name="value_reference_id" class="oe_edit_only" attrs="{'invisible': [('value_type','!=','reference')], 'required': [('value_type','=','reference')]}"/>
                                                                    <field name="value_time" class="oe_edit_only" attrs="{'invisible': [('value_type','!=','time')], 'required': [('value_type','=','time')]}"/>
                                                                    <field name="value_oid" class="oe_edit_only" attrs="{'invisible': [('value_type','!=','oid')], 'required': [('value_type','=','oid')]}"/>
                                                                    <field name="value_id" class="oe_edit_only" attrs="{'invisible': [('value_type','!=','id')], 'required': [('value_type','=','id')]}"/>
                                                                    <field name="value_unsigned_int" class="oe_edit_only" attrs="{'invisible': [('value_type','!=','unsigned_int')], 'required': [('value_type','=','unsigned_int')]}"/>
                                                                    <field name="value_positive_int" class="oe_edit_only" attrs="{'invisible': [('value_type','!=','positive_int')], 'required': [('value_type','=','positive_int')]}"/>
                                                                    <field name="value_annotation_id" class="oe_edit_only" attrs="{'invisible': [('value_type','!=','annotation')], 'required': [('value_type','=','annotation')]}"/>
                                                                    <field name="value_sampled_data_id" class="oe_edit_only" attrs="{'invisible': [('value_type','!=','sampled_data')], 'required': [('value_type','=','sampled_data')]}"/>
                                                                    <field name="value_meta_id" class="oe_edit_only" attrs="{'invisible': [('value_type','!=','meta')], 'required': [('value_type','=','meta')]}"/>
                                                                </group>
                                                                <group>
                                                                </group>
                                                            </group>
                                                        </sheet>
                                                    </form>
                                                </field>
                                            </page>
                                        </notebook>
                                    </sheet>
                                </form>
                            </page>
                        </notebook>
                    </sheet>
                </form>
            </field>
        </record>


        <act_window id="hc_res_healthcare_service_action"
                    name="HC Healthcare Services"
                    res_model="hc.res.healthcare.service"
                    view_mode="tree,form"
                    domain=""
                    context=""
                    limit=""/>

        <menuitem id="hc_healthcare_service.menu_hc_service"
                  name="Healthcare Services"
                  web_icon="hc_healthcare_service,static/description/icon.png"
                  parent="hc_base.menu_entity"
                  action="hc_res_healthcare_service_action"
                  groups="hc_base.group_hc_base_manager"
                  sequence="20"/>

        <!-- Service Category Views -->

        <record id="hc_vs_service_category_view_search" model="ir.ui.view">
            <field name="name">Service Category Search</field>
            <field name="model">hc.vs.service.category</field>
            <field name="arch" type="xml">
                <search string="Service Categories">
                    <field name="name" filter_domain="['|',('name','ilike',self),('definition','ilike',self)]"/>
                    <field name="code"/>
                    <field name="definition"/>
                    <group>
                        <filter name="group_by_parent" string="Parent" context="{'group_by':'contains_id'}"/>
                    </group>
                </search>
            </field>
        </record>

        <record id="hc_vs_service_category_view_tree" model="ir.ui.view">
            <field name="name">Service Category Tree</field>
            <field name="model">hc.vs.service.category</field>
            <field name="arch" type="xml">
                <tree string="Service Categories" default_order="name, code">
                    <field name="name"/>
                    <field name="code"/>
                    <field name="definition"/>
                    <field name="contains_id"/>
                    <field name="source_id" invisible="0"/>
                </tree>
            </field>
        </record>

        <record id="hc_vs_service_category_view_form" model="ir.ui.view">
            <field name="name">Service Category Form</field>
            <field name="model">hc.vs.service.category</field>
            <field name="arch" type="xml">
                <form string="Service Categories">
                    <sheet>
                        <h1>
                            <field name="name" default_focus="1" placeholder="Name (e.g., United States)"/>
                        </h1>
                        <field name="code" placeholder="Code (e.g., US)"/>
                        <field name="definition" placeholder="Definition"/>
                        <field name="comments" placeholder="Comments"/>
                        <group>
                            <group>
                                <field name="contains_id"/>
                                <field name="level" placeholder="An integer (e.g., 1, 2)"/>
                                <field name="is_abstract"/>
                                <field name="version" placeholder="e.g., v2.5"/>
                            </group>
                            <group>
                                <field name="source_id" placeholder="e.g., U.S. Census Bureau"/>
                                <field name="system" widget="url" placeholder="e.g., www.census.gov/"/>
                            </group>
                        </group>
                    </sheet>
                </form>
            </field>
        </record>

        <act_window id="hc_vs_service_category_action"
                    name="HC Service Categories"
                    res_model="hc.vs.service.category"
                    view_mode="tree,form"
                    domain=""
                    context=""
                    limit=""/>

        <menuitem id="hc_healthcare_service.menu_serv_cat"
                  name="Service Categories"
                  parent="hc_healthcare_service.menu_hc_service"
                  action="hc_vs_service_category_action"
                  groups="hc_base.group_hc_base_manager"
                  sequence="10"/>

        <!-- Service Provision Condition Views -->

        <record id="hc_vs_service_provision_condition_view_search" model="ir.ui.view">
            <field name="name">Service Provision Condition Search</field>
            <field name="model">hc.vs.service.provision.condition</field>
            <field name="arch" type="xml">
                <search string="Service Provision Conditions">
                    <field name="name" filter_domain="['|',('name','ilike',self),('definition','ilike',self)]"/>
                    <field name="code"/>
                    <field name="definition"/>
                    <group>
<!--                         <filter name="group_by_parent" string="Parent" context="{'group_by':'contains_id'}"/>    -->
                    </group>
                </search>
            </field>
        </record>

        <record id="hc_vs_service_provision_condition_view_tree" model="ir.ui.view">
            <field name="name">Service Provision Condition Tree</field>
            <field name="model">hc.vs.service.provision.condition</field>
            <field name="arch" type="xml">
                <tree string="Service Provision Conditions" default_order="name, code">
                    <field name="name"/>
                    <field name="code"/>
                    <field name="definition"/>
                    <field name="contains_id"/>
                    <field name="source_id" invisible="0"/>
                </tree>
            </field>
        </record>

        <record id="hc_vs_service_provision_condition_view_form" model="ir.ui.view">
            <field name="name">Service Provision Condition Form</field>
            <field name="model">hc.vs.service.provision.condition</field>
            <field name="arch" type="xml">
                <form string="Service Provision Conditions">
                    <sheet>
                        <h1>
                            <field name="name" default_focus="1" placeholder="Name (e.g., United States)"/>
                        </h1>
                        <field name="code" placeholder="Code (e.g., US)"/>
                        <field name="definition" placeholder="Definition"/>
                        <field name="comments" placeholder="Comments"/>
                        <group>
                            <group>
                                <field name="contains_id"/>
                                <field name="level" placeholder="An integer (e.g., 1, 2)"/>
                                <field name="is_abstract"/>
                                <field name="version" placeholder="e.g., v2.5"/>
                            </group>
                            <group>
                                <field name="source_id" placeholder="e.g., U.S. Census Bureau"/>
                                <field name="system" widget="url" placeholder="e.g., www.census.gov/"/>
                            </group>
                        </group>
                    </sheet>
                </form>
            </field>
        </record>

        <act_window id="hc_vs_service_provision_condition_action"
                    name="HC Service Provision Conditions"
                    res_model="hc.vs.service.provision.condition"
                    view_mode="tree,form"
                    domain=""
                    context=""
                    limit=""/>

        <menuitem id="hc_healthcare_service.menu_serv_prov_cond"
                  name="Service Provision Conditions"
                  parent="hc_healthcare_service.menu_hc_service"
                  action="hc_vs_service_provision_condition_action"
                  groups="hc_base.group_hc_base_manager"
                  sequence="20"/>

        <!-- Service Referral Method Views -->

        <record id="hc_vs_service_referral_method_view_search" model="ir.ui.view">
            <field name="name">Service Referral Method Search</field>
            <field name="model">hc.vs.service.referral.method</field>
            <field name="arch" type="xml">
                <search string="Service Referral Methods">
                    <field name="name" filter_domain="['|',('name','ilike',self),('definition','ilike',self)]"/>
                    <field name="code"/>
                    <field name="definition"/>
                    <group>
                    </group>
                </search>
            </field>
        </record>

        <record id="hc_vs_service_referral_method_view_tree" model="ir.ui.view">
            <field name="name">Service Referral Method Tree</field>
            <field name="model">hc.vs.service.referral.method</field>
            <field name="arch" type="xml">
                <tree string="Service Referral Methods" default_order="name, code">
                    <field name="name"/>
                    <field name="code"/>
                    <field name="definition"/>
                    <field name="contains_id"/>
                    <field name="source_id" invisible="0"/>
                </tree>
            </field>
        </record>

        <record id="hc_vs_service_referral_method_view_form" model="ir.ui.view">
            <field name="name">Service Referral Method Form</field>
            <field name="model">hc.vs.service.referral.method</field>
            <field name="arch" type="xml">
                <form string="Service Referral Methods">
                    <sheet>
                        <h1>
                            <field name="name" default_focus="1" placeholder="Name (e.g., United States)"/>
                        </h1>
                        <field name="code" placeholder="Code (e.g., US)"/>
                        <field name="definition" placeholder="Definition"/>
                        <field name="comments" placeholder="Comments"/>
                        <group>
                            <group>
                                <field name="contains_id"/>
                                <field name="level" placeholder="An integer (e.g., 1, 2)"/>
                                <field name="is_abstract"/>
                                <field name="version" placeholder="e.g., v2.5"/>
                            </group>
                            <group>
                                <field name="source_id" placeholder="e.g., U.S. Census Bureau"/>
                                <field name="system" widget="url" placeholder="e.g., www.census.gov/"/>
                            </group>
                        </group>
                    </sheet>
                </form>
            </field>
        </record>

        <act_window id="hc_vs_service_referral_method_action"
                    name="HC Service Referral Methods"
                    res_model="hc.vs.service.referral.method"
                    view_mode="tree,form"
                    domain=""
                    context=""
                    limit=""/>

        <menuitem id="hc_healthcare_service.menu_serv_ref_meth"
                  name="Service Referral Methods"
                  parent="hc_healthcare_service.menu_hc_service"
                  action="hc_vs_service_referral_method_action"
                  groups="hc_base.group_hc_base_manager"
                  sequence="30"/>

        <!-- Service Type Views -->

         <record id="hc_vs_service_type_view_search" model="ir.ui.view">
            <field name="name">Service Type Search</field>
            <field name="model">hc.vs.service.type</field>
            <field name="arch" type="xml">
                <search string="Service Types">
                    <field name="name" filter_domain="['|',('name','ilike',self),('definition','ilike',self)]"/>
                    <field name="code"/>
                    <field name="definition"/>
                    <group>
                        <filter name="group_by_parent" string="Parent" context="{'group_by':'contains_id'}"/>
                        <filter name="group_by_source" string="Source" context="{'group_by':'source_id'}"/>
                    </group>
                </search>
            </field>
        </record>

        <record id="hc_vs_service_type_view_tree" model="ir.ui.view">
            <field name="name">Service Type Tree</field>
            <field name="model">hc.vs.service.type</field>
            <field name="arch" type="xml">
                <tree string="Service Types" default_order="name, code">
                    <field name="name"/>
                    <field name="code"/>
                    <field name="definition"/>
                    <field name="contains_id"/>
                    <field name="source_id" invisible="0"/>
                </tree>
            </field>
        </record>

        <record id="hc_vs_service_type_view_form" model="ir.ui.view">
            <field name="name">Service Type Form</field>
            <field name="model">hc.vs.service.type</field>
            <field name="arch" type="xml">
                <form string="Service Types">
                    <sheet>
                        <h1>
                            <field name="name" default_focus="1" placeholder="Name (e.g., United States)"/>
                        </h1>
                        <field name="code" placeholder="Code (e.g., US)"/>
                        <field name="definition" placeholder="Definition"/>
                        <field name="comments" placeholder="Comments"/>
                        <group>
                            <group>
                                <field name="contains_id"/>
                                <field name="level" placeholder="An integer (e.g., 1, 2)"/>
                                <field name="is_abstract"/>
                                <field name="version" placeholder="e.g., v2.5"/>
                            </group>
                            <group>
                                <field name="source_id" placeholder="e.g., U.S. Census Bureau"/>
                                <field name="system" widget="url" placeholder="e.g., www.census.gov/"/>
                            </group>
                        </group>
                    </sheet>
                </form>
            </field>
        </record>

        <act_window id="hc_vs_service_type_action"
                    name="HC Service Types"
                    res_model="hc.vs.service.type"
                    view_mode="tree,form"
                    domain=""
                    context=""
                    limit=""/>

        <menuitem id="hc_healthcare_service.menu_serv_type"
                  name="Service Types"
                  parent="hc_healthcare_service.menu_hc_service"
                  action="hc_vs_service_type_action"
                  groups="hc_base.group_hc_base_manager"
                  sequence="40"/>

    </data>
</odoo>
